[
    {
        "key": "dbln",
        "value": "%7B%2261576925480570%22%3A%22WPHdR0gn%22%7D",
        "domain": "facebook.com",
        "path": "/login/device-based/",
        "hostOnly": false,
        "creation": "2025-06-07T15:12:27.255Z",
        "lastAccessed": "2025-06-07T15:12:27.256Z"
    },
    {
        "key": "datr",
        "value": "2tslaArPcQY6kNpOopPomWZI",
        "domain": "facebook.com",
        "path": "/",
        "hostOnly": false,
        "creation": "2025-06-07T15:12:27.256Z",
        "lastAccessed": "2025-06-07T15:12:27.256Z"
    },
    {
        "key": "sb",
        "value": "2tslaFxi_75zlNnycAJky3h7",
        "domain": "facebook.com",
        "path": "/",
        "hostOnly": false,
        "creation": "2025-06-07T15:12:27.256Z",
        "lastAccessed": "2025-06-07T15:12:27.256Z"
    },
    {
        "key": "ps_l",
        "value": "1",
        "domain": "facebook.com",
        "path": "/",
        "hostOnly": false,
        "creation": "2025-06-07T15:12:27.256Z",
        "lastAccessed": "2025-06-07T15:12:27.256Z"
    },
    {
        "key": "ps_n",
        "value": "1",
        "domain": "facebook.com",
        "path": "/",
        "hostOnly": false,
        "creation": "2025-06-07T15:12:27.256Z",
        "lastAccessed": "2025-06-07T15:12:27.256Z"
    },
    {
        "key": "oo",
        "value": "v1",
        "domain": "facebook.com",
        "path": "/",
        "hostOnly": false,
        "creation": "2025-06-07T15:12:27.256Z",
        "lastAccessed": "2025-06-07T15:12:27.256Z"
    },
    {
        "key": "locale",
        "value": "en_US",
        "domain": "facebook.com",
        "path": "/",
        "hostOnly": false,
        "creation": "2025-06-07T15:12:27.256Z",
        "lastAccessed": "2025-06-07T15:12:27.256Z"
    },
    {
        "key": "dpr",
        "value": "2.3014395236968994",
        "domain": "facebook.com",
        "path": "/",
        "hostOnly": false,
        "creation": "2025-06-07T15:12:27.256Z",
        "lastAccessed": "2025-06-07T15:12:27.256Z"
    },
    {
        "key": "vpd",
        "value": "v1%3B624x313x2.3014395236968994",
        "domain": "facebook.com",
        "path": "/",
        "hostOnly": false,
        "creation": "2025-06-07T15:12:27.256Z",
        "lastAccessed": "2025-06-07T15:12:27.256Z"
    },
    {
        "key": "c_user",
        "value": "61576925480570",
        "domain": "facebook.com",
        "path": "/",
        "hostOnly": false,
        "creation": "2025-06-07T15:12:27.256Z",
        "lastAccessed": "2025-06-07T15:12:27.256Z"
    },
    {
        "key": "xs",
        "value": "34%3A69UpMA87RjnGiQ%3A2%3A1749136853%3A-1%3A-1",
        "domain": "facebook.com",
        "path": "/",
        "hostOnly": false,
        "creation": "2025-06-07T15:12:27.256Z",
        "lastAccessed": "2025-06-07T15:12:27.256Z"
    },
    {
        "key": "fr",
        "value": "0WOSE1AvVplXXGQYE.AWd4q1bRRqHLNRIbX2lXFMLFsixrayiNm8PcDRN-supCY_ijWjY.BoPK4z..AAA.0.0.BoRFZz.AWcHU3_TGPju4px3s3HEB5cy2gs",
        "domain": "facebook.com",
        "path": "/",
        "hostOnly": false,
        "creation": "2025-06-07T15:12:27.256Z",
        "lastAccessed": "2025-06-07T15:12:27.256Z"
    },
    {
        "key": "fbl_st",
        "value": "100623825%3BT%3A29155151",
        "domain": "facebook.com",
        "path": "/",
        "hostOnly": false,
        "creation": "2025-06-07T15:12:27.256Z",
        "lastAccessed": "2025-06-07T15:12:27.256Z"
    },
    {
        "key": "wl_cbv",
        "value": "v2%3Bclient_version%3A2839%3Btimestamp%3A1749309043",
        "domain": "facebook.com",
        "path": "/",
        "hostOnly": false,
        "creation": "2025-06-07T15:12:27.256Z",
        "lastAccessed": "2025-06-07T15:12:27.256Z"
    }
]
